floral/__init__.py
floral/datasets.py
floral/graph.py
floral/loss.py
floral/nn.py
floral/optim.py
floral/visual.py
floral/data/mnist_labels_uint8
floral/data/mnist_sprite.png
floral-1.0.3.dist-info/METADATA
floral-1.0.3.dist-info/WHEEL
floral-1.0.3.dist-info/top_level.txt
floral-1.0.3.dist-info/zip-safe
floral-1.0.3.dist-info/RECORD
