Metadata-Version: 2.1
Name: floral
Version: 1.0.3
Summary: the best neural network library
Home-page: https://github.com/cryanwashere/Floral
Author: Cameron Ryan
Author-email: cjryanwashere@gmail.com
Project-URL: repository, https://github.com/cryanwashere/Floral
Classifier: Programming Language :: Python :: 3
Classifier: License :: OSI Approved :: MIT License
Classifier: Operating System :: OS Independent
Requires-Python: >=3.6
Requires-Dist: jax
Requires-Dist: jaxlib
Requires-Dist: numpy
Requires-Dist: Pillow
